{
  "id": "6e6e6b0b-0b95-46a6-b2c1-9624bf18014d",
  "prevId": "00000000-0000-0000-0000-000000000000",
  "version": "7",
  "dialect": "postgresql",
  "tables": {
    "public.events": {
      "name": "events",
      "schema": "",
      "columns": {
        "id": {
          "name": "id",
          "type": "uuid",
          "primaryKey": true,
          "notNull": true,
          "default": "gen_random_uuid()"
        },
        "title": {
          "name": "title",
          "type": "text",
          "primaryKey": false,
          "notNull": true
        },
        "summary": {
          "name": "summary",
          "type": "text",
          "primaryKey": false,
          "notNull": true
        },
        "category": {
          "name": "category",
          "type": "text",
          "primaryKey": false,
          "notNull": true
        },
        "severity": {
          "name": "severity",
          "type": "integer",
          "primaryKey": false,
          "notNull": true
        },
        "confidence": {
          "name": "confidence",
          "type": "real",
          "primaryKey": false,
          "notNull": true,
          "default": 1
        },
        "location": {
          "name": "location",
          "type": "geography(POINT, 4326)",
          "primaryKey": false,
          "notNull": true
        },
        "location_name": {
          "name": "location_name",
          "type": "text",
          "primaryKey": false,
          "notNull": true
        },
        "country_code": {
          "name": "country_code",
          "type": "text",
          "primaryKey": false,
          "notNull": false
        },
        "timestamp": {
          "name": "timestamp",
          "type": "timestamp with time zone",
          "primaryKey": false,
          "notNull": true
        },
        "sources": {
          "name": "sources",
          "type": "jsonb",
          "primaryKey": false,
          "notNull": true,
          "default": "'[]'::jsonb"
        },
        "media": {
          "name": "media",
          "type": "jsonb",
          "primaryKey": false,
          "notNull": true,
          "default": "'[]'::jsonb"
        },
        "raw_text": {
          "name": "raw_text",
          "type": "text",
          "primaryKey": false,
          "notNull": false
        },
        "situation_id": {
          "name": "situation_id",
          "type": "uuid",
          "primaryKey": false,
          "notNull": false
        },
        "expires_at": {
          "name": "expires_at",
          "type": "timestamp with time zone",
          "primaryKey": false,
          "notNull": false
        },
        "created_at": {
          "name": "created_at",
          "type": "timestamp with time zone",
          "primaryKey": false,
          "notNull": true,
          "default": "now()"
        },
        "updated_at": {
          "name": "updated_at",
          "type": "timestamp with time zone",
          "primaryKey": false,
          "notNull": true,
          "default": "now()"
        }
      },
      "indexes": {
        "events_timestamp_idx": {
          "name": "events_timestamp_idx",
          "columns": [
            {
              "expression": "timestamp",
              "isExpression": false,
              "asc": true,
              "nulls": "last"
            }
          ],
          "isUnique": false,
          "concurrently": false,
          "method": "btree",
          "with": {}
        },
        "events_category_idx": {
          "name": "events_category_idx",
          "columns": [
            {
              "expression": "category",
              "isExpression": false,
              "asc": true,
              "nulls": "last"
            }
          ],
          "isUnique": false,
          "concurrently": false,
          "method": "btree",
          "with": {}
        },
        "events_category_severity_time_idx": {
          "name": "events_category_severity_time_idx",
          "columns": [
            {
              "expression": "category",
              "isExpression": false,
              "asc": true,
              "nulls": "last"
            },
            {
              "expression": "severity",
              "isExpression": false,
              "asc": true,
              "nulls": "last"
            },
            {
              "expression": "timestamp",
              "isExpression": false,
              "asc": true,
              "nulls": "last"
            }
          ],
          "isUnique": false,
          "concurrently": false,
          "method": "btree",
          "with": {}
        }
      },
      "foreignKeys": {},
      "compositePrimaryKeys": {},
      "uniqueConstraints": {},
      "policies": {},
      "checkConstraints": {},
      "isRLSEnabled": false
    },
    "public.situations": {
      "name": "situations",
      "schema": "",
      "columns": {
        "id": {
          "name": "id",
          "type": "uuid",
          "primaryKey": true,
          "notNull": true,
          "default": "gen_random_uuid()"
        },
        "title": {
          "name": "title",
          "type": "text",
          "primaryKey": false,
          "notNull": true
        },
        "summary": {
          "name": "summary",
          "type": "text",
          "primaryKey": false,
          "notNull": true
        },
        "category": {
          "name": "category",
          "type": "text",
          "primaryKey": false,
          "notNull": true
        },
        "severity": {
          "name": "severity",
          "type": "integer",
          "primaryKey": false,
          "notNull": true
        },
        "country_code": {
          "name": "country_code",
          "type": "text",
          "primaryKey": false,
          "notNull": false
        },
        "location": {
          "name": "location",
          "type": "geography(POINT, 4326)",
          "primaryKey": false,
          "notNull": true
        },
        "radius_km": {
          "name": "radius_km",
          "type": "integer",
          "primaryKey": false,
          "notNull": true,
          "default": 50
        },
        "event_count": {
          "name": "event_count",
          "type": "integer",
          "primaryKey": false,
          "notNull": true,
          "default": 1
        },
        "first_seen": {
          "name": "first_seen",
          "type": "timestamp with time zone",
          "primaryKey": false,
          "notNull": true
        },
        "last_updated": {
          "name": "last_updated",
          "type": "timestamp with time zone",
          "primaryKey": false,
          "notNull": true
        },
        "status": {
          "name": "status",
          "type": "text",
          "primaryKey": false,
          "notNull": true,
          "default": "'active'"
        },
        "created_at": {
          "name": "created_at",
          "type": "timestamp with time zone",
          "primaryKey": false,
          "notNull": true,
          "default": "now()"
        },
        "updated_at": {
          "name": "updated_at",
          "type": "timestamp with time zone",
          "primaryKey": false,
          "notNull": true,
          "default": "now()"
        }
      },
      "indexes": {
        "situations_category_status_idx": {
          "name": "situations_category_status_idx",
          "columns": [
            {
              "expression": "category",
              "isExpression": false,
              "asc": true,
              "nulls": "last"
            },
            {
              "expression": "status",
              "isExpression": false,
              "asc": true,
              "nulls": "last"
            }
          ],
          "isUnique": false,
          "concurrently": false,
          "method": "btree",
          "with": {}
        },
        "situations_status_last_updated_idx": {
          "name": "situations_status_last_updated_idx",
          "columns": [
            {
              "expression": "status",
              "isExpression": false,
              "asc": true,
              "nulls": "last"
            },
            {
              "expression": "last_updated",
              "isExpression": false,
              "asc": true,
              "nulls": "last"
            }
          ],
          "isUnique": false,
          "concurrently": false,
          "method": "btree",
          "with": {}
        }
      },
      "foreignKeys": {},
      "compositePrimaryKeys": {},
      "uniqueConstraints": {},
      "policies": {},
      "checkConstraints": {},
      "isRLSEnabled": false
    }
  },
  "enums": {},
  "schemas": {},
  "sequences": {},
  "roles": {},
  "policies": {},
  "views": {},
  "_meta": {
    "columns": {},
    "schemas": {},
    "tables": {}
  }
}